synthetic_window_titles/common.py
synthetic_window_titles/constants.py
synthetic_window_titles/main.py
synthetic_window_titles/syntheticData.py
synthetic_window_titles/syntheticDataUsingRandomAugmentation.py
synthetic_window_titles/syntheticDataUsingSubstitution.py
synthetic_window_titles-0.1.0.dist-info/METADATA
synthetic_window_titles-0.1.0.dist-info/WHEEL
synthetic_window_titles-0.1.0.dist-info/RECORD
