Metadata-Version: 2.3
Name: synthetic-window-titles
Version: 0.1.0
Summary: This project helps create synthetic window titles for model training.
Author: qiblatainf
Author-email: qiblatain@live.com
Requires-Python: >=3.10
Classifier: Programming Language :: Python :: 3
Classifier: Programming Language :: Python :: 3.10
Classifier: Programming Language :: Python :: 3.11
Classifier: Programming Language :: Python :: 3.12
Classifier: Programming Language :: Python :: 3.13
Requires-Dist: nlpaug
Requires-Dist: torch
Requires-Dist: transformers
Project-URL: Repository, https://github.com/paxray/synthetic-window-titles
